pyduration/__init__.py
pyduration/duration.py
pyduration/util.py
pyduration-0.1.0.dist-info/entry_points.txt
pyduration-0.1.0.dist-info/LICENSE
pyduration-0.1.0.dist-info/WHEEL
pyduration-0.1.0.dist-info/METADATA
pyduration-0.1.0.dist-info/RECORD
