Metadata-Version: 2.1
Name: pyduration
Version: 0.1.0
Summary: A calendar unit length utility library.
Home-page: https://github.com/diatche/pyduration
License: MIT
Keywords: pyduration,calendar,length,unit,interval,date,date interval
Author: Pavel Diatchenko
Author-email: diatche@gmail.com
Requires-Python: >=3.5,<4
Classifier: License :: OSI Approved :: MIT License
Classifier: Programming Language :: Python :: 3
Classifier: Programming Language :: Python :: 3.5
Classifier: Programming Language :: Python :: 3.6
Classifier: Programming Language :: Python :: 3.7
Classifier: Programming Language :: Python :: 3.8
Classifier: Programming Language :: Python :: 3.9
Requires-Dist: arrow (>=0.12.1,<0.13.0)
Requires-Dist: intervalpy (>=0.1.0,<0.2.0)
Project-URL: Repository, https://github.com/diatche/pyduration
